channels/__init__.py
channels/apps.py
channels/auth.py
channels/consumer.py
channels/db.py
channels/exceptions.py
channels/layers.py
channels/middleware.py
channels/routing.py
channels/sessions.py
channels/utils.py
channels/worker.py
channels/generic/__init__.py
channels/generic/http.py
channels/generic/websocket.py
channels/management/__init__.py
channels/management/commands/__init__.py
channels/management/commands/runworker.py
channels/security/__init__.py
channels/security/websocket.py
channels/testing/__init__.py
channels/testing/application.py
channels/testing/http.py
channels/testing/live.py
channels/testing/websocket.py
channels-4.2.0.dist-info/LICENSE
channels-4.2.0.dist-info/METADATA
channels-4.2.0.dist-info/WHEEL
channels-4.2.0.dist-info/top_level.txt
channels-4.2.0.dist-info/RECORD
