Metadata-Version: 2.1
Name: channels
Version: 4.2.0
Summary: Brings async, event-driven capabilities to Django.
Home-page: http://github.com/django/channels
Author: Django Software Foundation
Author-email: foundation@djangoproject.com
License: BSD
Classifier: Development Status :: 5 - Production/Stable
Classifier: Environment :: Web Environment
Classifier: Intended Audience :: Developers
Classifier: License :: OSI Approved :: BSD License
Classifier: Operating System :: OS Independent
Classifier: Programming Language :: Python
Classifier: Programming Language :: Python :: 3
Classifier: Programming Language :: Python :: 3.8
Classifier: Programming Language :: Python :: 3.9
Classifier: Programming Language :: Python :: 3.10
Classifier: Programming Language :: Python :: 3.11
Classifier: Programming Language :: Python :: 3.12
Classifier: Framework :: Django
Classifier: Framework :: Django :: 4.2
Classifier: Framework :: Django :: 5.0
Classifier: Framework :: Django :: 5.1
Classifier: Topic :: Internet :: WWW/HTTP
Requires-Python: >=3.8
License-File: LICENSE
Requires-Dist: Django>=4.2
Requires-Dist: asgiref<4,>=3.6.0
Provides-Extra: tests
Requires-Dist: async-timeout; extra == "tests"
Requires-Dist: coverage~=4.5; extra == "tests"
Requires-Dist: pytest; extra == "tests"
Requires-Dist: pytest-django; extra == "tests"
Requires-Dist: pytest-asyncio; extra == "tests"
Provides-Extra: daphne
Requires-Dist: daphne>=4.0.0; extra == "daphne"
